{"stem":"1715","instances":[{"docId":"kraynag","docUri":"kraynag.html","score":3,"contexts":[{"form":"1715","weight":"1","pos":4201,"context":"...Bezüglich der Holzersparung wurde in der am 5. März <mark>1715<\/mark> abgehaltenen Konferenz jedoch entschieden: daß nach abgehaltenen Proben...","fid":"p__162"},{"form":"1715","weight":"1","pos":4311,"context":"...Daher auch untern 31ten Mai des nämlichen Jahres <mark>1715<\/mark> eine Hof-Verredung anlangte: den Inquisitions Process...","fid":"p__167"},{"form":"1715","weight":"1","pos":4339,"context":"...dies die Amtsberichte von 28. August und 6. November <mark>1715<\/mark> nachweisen. ","fid":"p__168"}]}]}