{"stem":"durchführung","instances":[{"docId":"kraynag","docUri":"kraynag.html","score":2,"contexts":[{"form":"Durchführung","weight":"1","pos":5652,"context":"...Idee, Schärfe der Auffassung und Consequenz in der <mark>Durchführung<\/mark> betrifft, hinter manchen abgewiesenen oder unberücksichtig gebliebenen Projekten...","fid":"p__234"},{"form":"Durchführung","weight":"1","pos":7119,"context":"...November 1760 erflossene Hofkammer Dekret überraschen, wonach die <mark>Durchführung<\/mark> dieser Proben dem Doctor medicinae in Botzen Johann Josef...","fid":"p__297"}]}]}