{"stem":"gegossenen","instances":[{"docId":"kraynag","docUri":"kraynag.html","score":2,"contexts":[{"form":"gegossenen","weight":"1","pos":1315,"context":"...erhalten. Das Feuerstück zunächst beim Schürofen aus vier <mark>gegossenen<\/mark> Eisenplatten ungefähr 10 Schuch lang und etwas weniger breit...","fid":"p__70"},{"form":"gegossenen","weight":"1","pos":9198,"context":"...ward auch ein Theil der Dörren zur Probe aus <mark>gegossenen<\/mark> Messingplatten zusammengestellt und wurde zur ","fid":"p__385"}]}]}