{"stem":"gubernial-bericht","instances":[{"docId":"kraynag","docUri":"kraynag.html","score":2,"contexts":[{"form":"Gubernial-Bericht","weight":"1","pos":8445,"context":" Dieses Gutachten ward in den <mark>Gubernial-Bericht<\/mark> einbezogen, das am 18. Dezember 1764 über die...","fid":"p__353"},{"form":"Gubernial-Berichte","weight":"1","pos":8668,"context":"...auf die Verbesserung der Dörrmanipulation, über welche der <mark>Gubernial-Berichte<\/mark> vom 29. Oktober obigen Jahres das Urtheil abgab:...","fid":"p__362"}]}]}