{"stem":"hilf","instances":[{"docId":"kraynag","docUri":"kraynag.html","score":2,"contexts":[{"form":"Hilfe","weight":"1","pos":425,"context":"...Dies irrigen Zeitbegriffe kamen dem allerdings mangelhaften Sudbetriebe zur <mark>Hilfe<\/mark> und das Pfannhausamt war mit egoistischer Rührigkeit beflissen den...","fid":"p__24"},{"form":"Hilfe","weight":"1","pos":2550,"context":"...Macht der Umstände kam somit der hallinnthalischen Sudmanipulation zur <mark>Hilfe<\/mark>, um ihr bereits erschüttertes Dasein wunderbarerwesie auf weitere...","fid":"p__102"}]}]}