{"stem":"indem","instances":[{"docId":"L4","docUri":"L4.html","score":2,"contexts":[{"form":"indeme","weight":"1","pos":178,"context":"...Störzingerischen Riße, und Anmerkungen abgeforderten Berichtes betrieben, <mark>indeme<\/mark> durch diesen Zeitraum die sorgfältigste Uiberlegung dieses wichtigen Gegenstandes...","fid":"p__4"},{"form":"indeme","weight":"1","pos":978,"context":"...eigentliche Ersparung an dem Holz Consummo zu verhoffen, <mark>indeme<\/mark> um die Hälfte, wo nicht um 2\/3tl weniger...","fid":"p__48"}]}]}