{"stem":"itz","instances":[{"docId":"L_modellbeschreibung","docUri":"L_modellbeschreibung.html","score":1,"contexts":[{"form":"itz","weight":"1","pos":554,"context":"...die Oefnung herauf, daß sie genug haben, und <mark>itz<\/mark> erst breiten die oberen Arbeiter das verhältnismäßige Quantum aus,...","fid":"p__109"}]},{"docId":"kraynag","docUri":"kraynag.html","score":1,"contexts":[{"form":"itze","weight":"1","pos":3988,"context":"...Salz-Proben Vormals im Jahre 1685 herausgegeben, <mark>itze<\/mark> aber seiner Nutzbarkeit wegen der curiosen Welt zu Dienste...","fid":"p__157"}]}]}