{"stem":"nächst","instances":[{"docId":"kraynag","docUri":"kraynag.html","score":2,"contexts":[{"form":"nächst","weight":"1","pos":4864,"context":"...ein oder andere bestens möge verrichtet und befördert werden; <mark>nächst<\/mark> gehorsamer Wiederhollung unsere in puncto des Salzsuds contra den...","fid":"p__197"},{"form":"nächst","weight":"1","pos":9424,"context":"...als wirdt derselbe und ihr bestens befleissen sein [<mark>nächst<\/mark> seite] solche verordnung und vernastaltung zu thuen d....","fid":"note__1"}]},{"docId":"L3","docUri":"L3.html","score":1,"contexts":[{"form":"nächst","weight":"1","pos":2129,"context":"...OOen [Wesen] an, daß selbes Vorhabens sey <mark>nächst<\/mark> künftiger Erchtag als den 6ten Juny geliebts Gott...","fid":"p__54"}]}]}