{"stem":"nämlichen","instances":[{"docId":"kraynag","docUri":"kraynag.html","score":4,"contexts":[{"form":"nämlichen","weight":"1","pos":4309,"context":" Daher auch untern 31ten Mai des <mark>nämlichen<\/mark> Jahres 1715 eine Hof-Verredung anlangte: den...","fid":"p__167"},{"form":"nämlichen","weight":"1","pos":5926,"context":"...in Verwahrung gebracht wurde. Weiter heißt es in dem <mark>nämlichen<\/mark> Bericht: „Heut in der Früh, da...","fid":"p__244"},{"form":"nämlichen","weight":"1","pos":6421,"context":"...11. August 1760 und wurde dasselbe am 14. des <mark>nämlichen<\/mark> dem Professor Sterzinger zur Eröffnung seiner Gegengründe mitgetheilt....","fid":"p__264"},{"form":"nämlichen","weight":"1","pos":6632,"context":"...den verschiedenen Feuersgrad an, indem durch selben aus der <mark>nämlichen<\/mark> Sur verschiedene Salzgattungen erzeugt werden können. Bei dem neueren...","fid":"p__273"}]}]}