{"stem":"schmid","instances":[{"docId":"kraynag","docUri":"kraynag.html","score":1,"contexts":[{"form":"Schmid","weight":"1","pos":3902,"context":"...- [Pennladen] – Urent – Affenbaum, <mark>Schmid<\/mark> Weiß und- Schwarzschluder- Salz auch Merkentest gewohnt sind,...","fid":"p__152"}]},{"docId":"L2","docUri":"L2.html","score":1,"contexts":[{"form":"Schmid","weight":"1","pos":636,"context":"...jedem dieser drey Pfannhäußer waren 32 Arbeiter, ein <mark>Schmid<\/mark>, und ein Zimmermeister angestellt. ","fid":"p__37"}]}]}