{"stem":"schweif","instances":[{"docId":"kraynag","docUri":"kraynag.html","score":2,"contexts":[{"form":"Schweif","weight":"1","pos":2744,"context":"...kehrten den Kübel öfters um und setzten einen größeren <mark>Schweif<\/mark> oder Spitzen darauf, wodurch sehr vieles Salz zum großen...","fid":"p__110"},{"form":"Schweif","weight":"1","pos":2765,"context":"...in Koth herumgezogen wurden, wodurch viele Stücke besonders vom <mark>Schweif<\/mark> oder Kopf herabgebrochen und mit Füßen getretten, sodann...","fid":"p__110"}]}]}