{"stem":"vornam","instances":[{"docId":"L_modellbeschreibung","docUri":"L_modellbeschreibung.html","score":12,"contexts":[{"form":"Vorname","weight":"1","pos":904,"context":"<mark>Vorname<\/mark>: Nachname: geboren: gestorben:  ","fid":"div__16"},{"form":"Vorname","weight":"1","pos":909,"context":"<mark>Vorname<\/mark>: Nachname: geboren: gestorben:  ","fid":"div__16"},{"form":"Vorname","weight":"1","pos":914,"context":"<mark>Vorname<\/mark>: Nachname: geboren: gestorben:  ","fid":"div__16"},{"form":"Vorname","weight":"1","pos":919,"context":"<mark>Vorname<\/mark>: Nachname: geboren: gestorben:  ","fid":"div__16"},{"form":"Vorname","weight":"1","pos":924,"context":"<mark>Vorname<\/mark>: Nachname: geboren: gestorben:  ","fid":"div__16"},{"form":"Vorname","weight":"1","pos":929,"context":"<mark>Vorname<\/mark>: Nachname: geboren: gestorben:  ","fid":"div__16"},{"form":"Vorname","weight":"1","pos":934,"context":"<mark>Vorname<\/mark>: Nachname: geboren: gestorben:  ","fid":"div__16"},{"form":"Vorname","weight":"1","pos":939,"context":"<mark>Vorname<\/mark>: Nachname: geboren: gestorben:  ","fid":"div__16"},{"form":"Vorname","weight":"1","pos":944,"context":"<mark>Vorname<\/mark>: Nachname: geboren: gestorben:  ","fid":"div__16"},{"form":"Vorname","weight":"1","pos":949,"context":"<mark>Vorname<\/mark>: Nachname: geboren: gestorben:  ","fid":"div__16"},{"form":"Vorname","weight":"1","pos":954,"context":"<mark>Vorname<\/mark>: Nachname: geboren: gestorben:  ","fid":"div__16"},{"form":"Vorname","weight":"1","pos":959,"context":"<mark>Vorname<\/mark>: Nachname: geboren: gestorben:  ","fid":"div__16"}]},{"docId":"waldauf","docUri":"waldauf.html","score":12,"contexts":[{"form":"Vorname","weight":"1","pos":599,"context":"<mark>Vorname<\/mark>: Nachname: geboren: gestorben:  ","fid":"div__16"},{"form":"Vorname","weight":"1","pos":604,"context":"<mark>Vorname<\/mark>: Nachname: geboren: gestorben:  ","fid":"div__16"},{"form":"Vorname","weight":"1","pos":609,"context":"<mark>Vorname<\/mark>: Nachname: geboren: gestorben:  ","fid":"div__16"},{"form":"Vorname","weight":"1","pos":614,"context":"<mark>Vorname<\/mark>: Nachname: geboren: gestorben:  ","fid":"div__16"},{"form":"Vorname","weight":"1","pos":619,"context":"<mark>Vorname<\/mark>: Nachname: geboren: gestorben:  ","fid":"div__16"},{"form":"Vorname","weight":"1","pos":624,"context":"<mark>Vorname<\/mark>: Nachname: geboren: gestorben:  ","fid":"div__16"},{"form":"Vorname","weight":"1","pos":629,"context":"<mark>Vorname<\/mark>: Nachname: geboren: gestorben:  ","fid":"div__16"},{"form":"Vorname","weight":"1","pos":634,"context":"<mark>Vorname<\/mark>: Nachname: geboren: gestorben:  ","fid":"div__16"},{"form":"Vorname","weight":"1","pos":639,"context":"<mark>Vorname<\/mark>: Nachname: geboren: gestorben:  ","fid":"div__16"},{"form":"Vorname","weight":"1","pos":644,"context":"<mark>Vorname<\/mark>: Nachname: geboren: gestorben:  ","fid":"div__16"},{"form":"Vorname","weight":"1","pos":649,"context":"<mark>Vorname<\/mark>: Nachname: geboren: gestorben:  ","fid":"div__16"},{"form":"Vorname","weight":"1","pos":654,"context":"<mark>Vorname<\/mark>: Nachname: geboren: gestorben:  ","fid":"div__16"}]},{"docId":"L2","docUri":"L2.html","score":11,"contexts":[{"form":"Vorname","weight":"1","pos":1928,"context":"<mark>Vorname<\/mark>: Nachname: geboren: gestorben:  ","fid":"div__15"},{"form":"Vorname","weight":"1","pos":1933,"context":"<mark>Vorname<\/mark>: Nachname: geboren: gestorben:  ","fid":"div__15"},{"form":"Vorname","weight":"1","pos":1938,"context":"<mark>Vorname<\/mark>: Nachname: geboren: gestorben:  ","fid":"div__15"},{"form":"Vorname","weight":"1","pos":1943,"context":"<mark>Vorname<\/mark>: Nachname: geboren: gestorben:  ","fid":"div__15"},{"form":"Vorname","weight":"1","pos":1948,"context":"<mark>Vorname<\/mark>: Nachname: geboren: gestorben:  ","fid":"div__15"},{"form":"Vorname","weight":"1","pos":1953,"context":"<mark>Vorname<\/mark>: Nachname: geboren: gestorben:  ","fid":"div__15"},{"form":"Vorname","weight":"1","pos":1958,"context":"<mark>Vorname<\/mark>: Nachname: geboren: gestorben:  ","fid":"div__15"},{"form":"Vorname","weight":"1","pos":1963,"context":"<mark>Vorname<\/mark>: Nachname: geboren: gestorben:  ","fid":"div__15"},{"form":"Vorname","weight":"1","pos":1968,"context":"<mark>Vorname<\/mark>: Nachname: geboren: gestorben:  ","fid":"div__15"},{"form":"Vorname","weight":"1","pos":1973,"context":"<mark>Vorname<\/mark>: Nachname: geboren: gestorben:  ","fid":"div__15"},{"form":"Vorname","weight":"1","pos":1978,"context":"<mark>Vorname<\/mark>: Nachname: geboren: gestorben:  ","fid":"div__15"}]}]}