{"stem":"wild","instances":[{"docId":"kraynag","docUri":"kraynag.html","score":1,"contexts":[{"form":"wild","weight":"1","pos":1011,"context":"...ist er Fezius mit Verpfändung Leib und Seel so <mark>wild<\/mark> daß sich gleich darob zu zu entsetzen; [...","fid":"p__50"}]},{"docId":"L2","docUri":"L2.html","score":1,"contexts":[{"form":"Wilde","weight":"1","pos":968,"context":"...zu finden seyen, in welcher sich häufig solche <mark>Wilde<\/mark> anlegen. 5tens - Fliesse alldort die Sulze...","fid":"p__66"}]}]}