{"stem":"öfen","instances":[{"docId":"kraynag","docUri":"kraynag.html","score":3,"contexts":[{"form":"Öfen","weight":"1","pos":3105,"context":"...: die fehlerhafte Lage der Feuerstätten, da die <mark>Öfen<\/mark> bald gegen die rechte Seite der Pfannstatt hinein geführt...","fid":"p__126"},{"form":"Öfen","weight":"1","pos":4893,"context":"..., breit und eben so tief aus Kupferblech verfertigte <mark>Öfen<\/mark> einzustellen. ","fid":"p__196"},{"form":"Öfen","weight":"1","pos":5794,"context":"...Regengüßen eine derartige Anschwellung des Innstromes, daß die <mark>Öfen<\/mark> der Pfannen unter Wasser gesetzt wurden und der Sudbetrieb...","fid":"p__238"}]}]}